django_pint_field/__init__.py
django_pint_field/adapters.py
django_pint_field/aggregates.py
django_pint_field/app_settings.py
django_pint_field/apps.py
django_pint_field/exceptions.py
django_pint_field/forms.py
django_pint_field/helpers.py
django_pint_field/indexes.py
django_pint_field/lookups.py
django_pint_field/models.py
django_pint_field/rest.py
django_pint_field/units.py
django_pint_field/validation.py
django_pint_field/widgets.py
django_pint_field/migrations/0001_create_composite_fields.py
django_pint_field/migrations/0002_consolidate_composite_fields.py
django_pint_field/migrations/__init__.py
django_pint_field/templatetags/__init__.py
django_pint_field/templatetags/django_pint_field.py
django_pint_field-2026.1.3.dist-info/licenses/LICENSE
django_pint_field-2026.1.3.dist-info/METADATA
django_pint_field-2026.1.3.dist-info/WHEEL
django_pint_field-2026.1.3.dist-info/top_level.txt
django_pint_field-2026.1.3.dist-info/RECORD
