Metadata-Version: 2.4
Name: django-pint-field
Version: 2026.1.3
Summary: Unit Conversion fields for Django and Postgres
Author-email: Jack Linke <jacklinke@gmail.com>
License-Expression: MIT
Project-URL: Homepage, https://github.com/OmenApps/django-pint-field
Project-URL: Repository, https://github.com/OmenApps/django-pint-field
Project-URL: Documentation, https://django-pint-field.readthedocs.io/en/latest/
Project-URL: Changelog, https://github.com/OmenApps/django-pint-field/releases
Classifier: Environment :: Web Environment
Classifier: Framework :: Django
Classifier: Framework :: Django :: 4.2
Classifier: Framework :: Django :: 5.0
Classifier: Framework :: Django :: 5.1
Classifier: Framework :: Django :: 5.2
Classifier: Development Status :: 4 - Beta
Classifier: Intended Audience :: Developers
Classifier: Operating System :: OS Independent
Classifier: Programming Language :: Python
Classifier: Programming Language :: Python :: 3
Classifier: Programming Language :: Python :: 3.11
Classifier: Programming Language :: Python :: 3.12
Classifier: Programming Language :: Python :: 3.13
Classifier: Programming Language :: Python :: 3.14
Classifier: Topic :: Internet :: WWW/HTTP
Classifier: Topic :: Internet :: WWW/HTTP :: Dynamic Content
Classifier: Topic :: Software Development :: Libraries :: Python Modules
Requires-Python: <4.0,>=3.11
License-File: LICENSE
Requires-Dist: django>=4.2.25
Requires-Dist: pint>=0.24
Dynamic: license-file
